playback/__init__.py
playback/api.py
playback/cinder.py
playback/cli.py
playback/cmd.py
playback/common.py
playback/config.py
playback/env.py
playback/glance.py
playback/haproxy.py
playback/haproxy_config.py
playback/haproxy_install.py
playback/horizon.py
playback/keystone.py
playback/manila.py
playback/manila_share.py
playback/mysql.py
playback/mysql_config.py
playback/mysql_installation.py
playback/mysql_manage.py
playback/neutron.py
playback/neutron_agent.py
playback/nova.py
playback/nova_compute.py
playback/prepare_host.py
playback/rabbitmq.py
playback/swift.py
playback/swift_storage.py
playback/templates/__init__.py
playback/templates/account_server_conf.py
playback/templates/cinder_conf.py
playback/templates/container_server_conf.py
playback/templates/dhcp_agent_ini.py
playback/templates/dnsmasq_neutron_conf.py
playback/templates/external_interface.py
playback/templates/galera_list.py
playback/templates/glance_api_conf.py
playback/templates/glance_registry_conf.py
playback/templates/haproxy_cfg.py
playback/templates/keepalived_conf.py
playback/templates/keystone_conf.py
playback/templates/keystone_paste_ini.py
playback/templates/l3_agent_ini.py
playback/templates/libvirt_bin.py
playback/templates/libvirtd_conf.py
playback/templates/linuxbridge_agent_ini.py
playback/templates/linuxbridge_agent_ini_for_agent.py
playback/templates/local_settings_py.py
playback/templates/manila_conf.py
playback/templates/manila_conf_for_share.py
playback/templates/memcached_conf.py
playback/templates/metadata_agent_ini.py
playback/templates/ml2_conf_ini.py
playback/templates/my_cnf.py
playback/templates/my_cnf_xenial.py
playback/templates/neutron_conf.py
playback/templates/neutron_conf_for_agent.py
playback/templates/nova_compute_conf.py
playback/templates/nova_conf.py
playback/templates/nova_conf_for_compute.py
playback/templates/object_server_conf.py
playback/templates/policy_json_for_cinder.py
playback-0.3.9.dist-info/DESCRIPTION.rst
playback-0.3.9.dist-info/METADATA
playback-0.3.9.dist-info/RECORD
playback-0.3.9.dist-info/WHEEL
playback-0.3.9.dist-info/entry_points.txt
playback-0.3.9.dist-info/metadata.json
playback-0.3.9.dist-info/top_level.txt
