Metadata-Version: 2.0
Name: playback
Version: 0.3.9
Summary: OpenStack provisioning and orchestration library
Home-page: https://github.com/jiasir/playback/
Author: jiasir
Author-email: jiasir@icloud.com
License: MIT
Platform: UNKNOWN
Requires-Dist: PyYAML (==3.11)
Requires-Dist: ecdsa (==0.13)
Requires-Dist: fabric (==1.10.2)
Requires-Dist: jinja2 (==2.8)
Requires-Dist: markupsafe (==0.23)
Requires-Dist: paramiko (==1.16.0)
Requires-Dist: pycrypto (==2.6.1)
Requires-Dist: setuptools (==19.6.2)
Requires-Dist: tqdm (==3.8.0)
